setup.py
yandex.translate.egg-info/PKG-INFO
yandex.translate.egg-info/SOURCES.txt
yandex.translate.egg-info/dependency_links.txt
yandex.translate.egg-info/requires.txt
yandex.translate.egg-info/top_level.txt
yandex_translate/__init__.py