Metadata-Version: 1.1
Name: yandex.translate
Version: 0.3.4
Summary: Python library for Yandex.Translate API.
Home-page: https://github.com/valmet/python-yandex-translate
Author: Nae Tennouji
Author-email: me@require.pm
License: DO WHAT THE FUCK YOU WANT TO PUBLIC LICENSE
Keywords: yandex yandex-translate translate
Platform: All
Classifier: Intended Audience :: Developers
Classifier: Development Status :: 3 - Alpha
Classifier: Operating System :: OS Independent
Classifier: Programming Language :: Python
Classifier: Programming Language :: Python :: 2.7
Classifier: Programming Language :: Python :: 3.3
Provides: yandex_translate
